bpmscan/__init__.py
bpmscan/app.py
bpmscan/conf.py
bpmscan/facetracker.py
bpmscan/person.py
bpmscan/plot.py
bpmscan/sceneanalyzer.py
bpmscan/util.py
bpmscan/videostream.py
bpmscan/widgets.py
bpmscan/data/lbpcascade_frontalface_improved.xml
bpmscan-0.1.2.dist-info/LICENSE
bpmscan-0.1.2.dist-info/METADATA
bpmscan-0.1.2.dist-info/WHEEL
bpmscan-0.1.2.dist-info/entry_points.txt
bpmscan-0.1.2.dist-info/top_level.txt
bpmscan-0.1.2.dist-info/RECORD
