Metadata-Version: 2.1
Name: bpmscan
Version: 0.1.2
Summary: Measures heart rate of multiple person realtime from Webcamera, IPCamera and also from from Uploaded video
Home-page: https://github.com/coderganesh/heartpi
Author: Ganesh Kumar T K
Author-email: ganeshkumartk@outlook.com
License: MIT
Keywords: rPPG heartbeat webcam
Platform: UNKNOWN
Classifier: Development Status :: 2 - Pre-Alpha
Classifier: Intended Audience :: Science/Research
Classifier: Intended Audience :: Healthcare Industry
Classifier: Intended Audience :: End Users/Desktop
Classifier: Intended Audience :: Developers
Classifier: Topic :: Scientific/Engineering :: Image Processing
Classifier: Topic :: Scientific/Engineering :: Medical Science Apps.
Classifier: Topic :: Scientific/Engineering :: Visualization
Classifier: License :: OSI Approved :: MIT License
Classifier: Programming Language :: Python :: 3.6
Classifier: Programming Language :: Python :: 3 :: Only
Requires-Dist: PyQt5
Requires-Dist: PyQtChart
Requires-Dist: eventkit
Requires-Dist: numpy
Requires-Dist: opencv-python
Requires-Dist: scipy
